AUTHORS
ChangeLog
README.md
mistral_k8s_actions.py
setup.cfg
setup.py
testk8s.txt
tox.ini
./mistral_k8s_actions.py
mistral_k8s_actions.egg-info/PKG-INFO
mistral_k8s_actions.egg-info/SOURCES.txt
mistral_k8s_actions.egg-info/dependency_links.txt
mistral_k8s_actions.egg-info/entry_points.txt
mistral_k8s_actions.egg-info/not-zip-safe
mistral_k8s_actions.egg-info/pbr.json
mistral_k8s_actions.egg-info/top_level.txt